sleuth_kit/__init__.py
sleuth_kit/api/__init__.py
sleuth_kit/api/transpose.py
sleuth_kit/cli/__init__.py
sleuth_kit/cli/sleuth.py
sleuth_kit/config.py
sleuth_kit/data/__init__.py
sleuth_kit/helpers/__init__.py
sleuth_kit/helpers/setup_schema.py
sleuth_kit/helpers/storage.py
sleuth_kit/sql/ethereum_accounts.sql
sleuth_kit/sql/ethereum_transactions.sql
sleuth_kit-0.0.1.dist-info/LICENSE
sleuth_kit-0.0.1.dist-info/METADATA
sleuth_kit-0.0.1.dist-info/WHEEL
sleuth_kit-0.0.1.dist-info/entry_points.txt
sleuth_kit-0.0.1.dist-info/RECORD
