Metadata-Version: 2.1
Name: sleuth-kit
Version: 0.0.1
Summary: A flexible and extensible toolkit designed for blockchain investigation and intelligence gathering.
Home-page: https://sleuth.fi
License: MIT
Author: Sleuth
Author-email: dev@sleuth.fi
Requires-Python: >=3.12,<4.0
Classifier: License :: OSI Approved :: MIT License
Classifier: Programming Language :: Python :: 3
Classifier: Programming Language :: Python :: 3.12
Requires-Dist: click (>=8.1.7,<9.0.0)
Requires-Dist: colorama (>=0.4.6,<0.5.0)
Requires-Dist: python-dotenv (>=1.0.1,<2.0.0)
Requires-Dist: requests (>=2.32.3,<3.0.0)
Requires-Dist: tqdm (>=4.66.5,<5.0.0)
Project-URL: Documentation, https://docs.sleuth.fi
Project-URL: Repository, https://github.com/sleuthfi/sleuth-kit
